{"skeleton":{"hash":"ytlUWbrdXMs","spine":"4.1.24","x":-96,"y":-95,"width":192,"height":215.6,"images":"../Anim/Sale/","audio":""},"bones":[{"name":"root"},{"name":"bone","parent":"root","x":-58.98,"y":83.79}],"slots":[{"name":"Group 271 copy 3","bone":"root","attachment":"Group 271 copy 3"},{"name":"Coin","bone":"root"},{"name":"Layer 885","bone":"root"},{"name":"hot","bone":"bone","attachment":"hot"}],"skins":[{"name":"default","attachments":{"Group 271 copy 3":{"Group 271 copy 3":{"width":192,"height":190}},"hot":{"hot":{"x":1.79,"y":-1.19,"width":75,"height":76}}}}],"animations":{"animation":{"bones":{"bone":{"rotate":[{"value":26.14},{"time":0.3333},{"time":0.6667,"value":26.14}]}}}}}