{"skeleton":{"hash":"8fIrYneot6k","spine":"4.1.24","x":-37.24,"y":-42.5,"width":62.24,"height":85,"images":"D:/Yang/Dev_Giang/TripleMatchCity/Anim/phone","audio":""},"bones":[{"name":"root"},{"name":"bone","parent":"root","length":17.89,"rotation":-142.5,"x":-7.42,"y":9.07},{"name":"bone2","parent":"root","x":-25.84,"y":-0.08}],"slots":[{"name":"Shape 1","bone":"bone","attachment":"Shape 1"},{"name":"Group 56","bone":"root","attachment":"Group 56"},{"name":"Layer 1","bone":"bone2","attachment":"Layer 1"}],"skins":[{"name":"default","attachments":{"Group 56":{"Group 56":{"width":50,"height":85}},"Layer 1":{"Layer 1":{"x":-0.9,"y":0.28,"width":21,"height":33}},"Shape 1":{"Shape 1":{"x":11.88,"y":0.69,"rotation":142.5,"width":23,"height":21}}}}],"animations":{"animation":{"bones":{"bone":{"rotate":[{},{"time":1,"value":-19.66},{"time":2}]},"bone2":{"translate":[{},{"time":1,"x":-2.58,"y":7.53},{"time":2}]}}}}}